mock/__init__.py
mock/backports.py
mock/mock.py
mock-5.1.0.dist-info/LICENSE.txt
mock-5.1.0.dist-info/METADATA
mock-5.1.0.dist-info/WHEEL
mock-5.1.0.dist-info/top_level.txt
mock-5.1.0.dist-info/RECORD
