Metadata-Version: 2.1
Name: mock
Version: 5.1.0
Summary: Rolling backport of unittest.mock for all Pythons
Home-page: http://mock.readthedocs.org/en/latest/
Author: Testing Cabal
Author-email: testing-in-python@lists.idyll.org
Project-URL: Source, https://github.com/testing-cabal/mock
Classifier: Development Status :: 5 - Production/Stable
Classifier: Environment :: Console
Classifier: Intended Audience :: Developers
Classifier: License :: OSI Approved :: BSD License
Classifier: Operating System :: OS Independent
Classifier: Programming Language :: Python
Classifier: Programming Language :: Python :: 3.6
Classifier: Programming Language :: Python :: 3.7
Classifier: Programming Language :: Python :: 3.8
Classifier: Programming Language :: Python :: 3.9
Classifier: Programming Language :: Python :: 3.10
Classifier: Programming Language :: Python :: 3.11
Classifier: Programming Language :: Python :: Implementation :: CPython
Classifier: Programming Language :: Python :: Implementation :: PyPy
Classifier: Topic :: Software Development :: Libraries
Classifier: Topic :: Software Development :: Libraries :: Python Modules
Classifier: Topic :: Software Development :: Testing
Requires-Python: >=3.6
Provides-Extra: docs
Provides-Extra: test
Provides-Extra: build
License-File: LICENSE.txt
